README.md
setup.cfg
setup.py
pyshaun/__init__.py
pyshaun/decoder.py
pyshaun/numeric.py
pyshaun/prettyprinter.py
pyshaun.egg-info/PKG-INFO
pyshaun.egg-info/SOURCES.txt
pyshaun.egg-info/dependency_links.txt
pyshaun.egg-info/top_level.txt