Metadata-Version: 1.1
Name: pyshaun
Version: 0.1.6
Summary: SHAUN implementation
Home-page: https://github.com/ablanleuil/pyshaun
Author: Arthur Blanleuil
Author-email: arthur.blanleuil@gmail.com
License: UNKNOWN
Download-URL: https://github.com/ablanleuil/pyshaun/archive/0.0.1.tar.gz
Keywords: notation language,library
Platform: UNKNOWN
Classifier: Programming Language :: Python
Classifier: Programming Language :: Python :: 3
Classifier: License :: OSI Approved :: MIT License
Classifier: Operating System :: OS Independent
